examples/steps/__init__.py
examples/steps/check_website_title.py
examples/test_cases/__init__.py
examples/test_cases/website_titles.py
marvin/__init__.py
marvin/exceptions.py
marvin/version.py
marvin/core/__init__.py
marvin/core/context.py
marvin/core/reportable.py
marvin/core/status.py
marvin/core/step.py
marvin/core/step_runner.py
marvin/core/step_running_context.py
marvin/core/suite.py
marvin/core/test_runner.py
marvin/core/test_running_context.py
marvin/core/test_script.py
marvin/data/__init__.py
marvin/data/data_provider.py
marvin/data/data_provider_registry.py
marvin/data/file_data_provider.py
marvin/data/iteration_data.py
marvin/data/data_providers/__init__.py
marvin/data/data_providers/null_data_provider.py
marvin/data/data_providers/yaml_data_provider.py
marvin/report/__init__.py
marvin/report/events.py
marvin/report/publisher.py
marvin/report/observers/__init__.py
marvin/report/observers/elk_reporter.py
marvin/report/observers/event_logger.py
marvin/runner/__init__.py
marvin/runner/cli.py
marvin/runner/runner.py
marvin/runner/runtime_suite.py
marvin/util/__init__.py
marvin/util/compat.py
marvin/util/config.py
marvin/util/files.py
marvin_test-1.0.1.dist-info/DESCRIPTION.rst
marvin_test-1.0.1.dist-info/METADATA
marvin_test-1.0.1.dist-info/RECORD
marvin_test-1.0.1.dist-info/WHEEL
marvin_test-1.0.1.dist-info/entry_points.txt
marvin_test-1.0.1.dist-info/metadata.json
marvin_test-1.0.1.dist-info/top_level.txt
tests/resources/__init__.py
tests/resources/runner/__init__.py
tests/resources/runner/marvin_conf.py
tests/stubs/__init__.py
tests/stubs/builders.py
tests/stubs/dummies.py
tests/stubs/exception.py
